numpypy/PyPyNum.png
numpypy/README.md
numpypy/__init__.py
numpypy-1.17.2.dist-info/METADATA
numpypy-1.17.2.dist-info/WHEEL
numpypy-1.17.2.dist-info/top_level.txt
numpypy-1.17.2.dist-info/RECORD
